README.md
setup.py
dapeng/__init__.py
dapeng/dapeng.py
dapeng/dapeng_api.py
dapeng/dpc.py
dapeng/settings.py
dapeng/util.py
dapeng/version.py
dapeng_cli.egg-info/PKG-INFO
dapeng_cli.egg-info/SOURCES.txt
dapeng_cli.egg-info/dependency_links.txt
dapeng_cli.egg-info/entry_points.txt
dapeng_cli.egg-info/requires.txt
dapeng_cli.egg-info/top_level.txt